{
  "name": "ehdev-shell",
  "installname": "ehdev-shell",
  "type": "AppImage",
  "description": "An electron based developing tool for feds.",
  "authors": [
    {
      "name": "EHDFE",
      "url": "https://github.com/EHDFE"
    }
  ],
  "links": [
    {
      "type": "GitHub",
      "url": "EHDFE/ehdev-shell"
    },
    {
      "type": "Download",
      "url": "https://github.com/EHDFE/ehdev-shell/releases"
    }
  ],
  "installinfo": [
    {
      "version": "Not Installed",
      "size": "Not Installed",
      "tag": "Not Installed",
      "status": "Not Installed"
    }
  ]
}
