{
  "name": "Gigantum",
  "installname": "gigantum",
  "type": "AppImage",
  "description": "Gigantum",
  "authors": [
    {
      "name": "gigantum",
      "url": "https://github.com/gigantum"
    }
  ],
  "links": [
    {
      "type": "GitHub",
      "url": "gigantum/gigantum-desktop"
    },
    {
      "type": "Download",
      "url": "https://github.com/gigantum/gigantum-desktop/releases"
    }
  ],
  "installinfo": [
    {
      "version": "Not Installed",
      "size": "Not Installed",
      "tag": "Not Installed",
      "status": "Not Installed"
    }
  ]
}
