{
  "name": "MyCrypto",
  "installname": "mycrypto",
  "type": "AppImage",
  "description": "MyCrypto web and electron app",
  "authors": [
    {
      "name": "MyCryptoHQ",
      "url": "https://github.com/MyCryptoHQ"
    }
  ],
  "links": [
    {
      "type": "GitHub",
      "url": "MyCryptoHQ/MyCrypto"
    },
    {
      "type": "Download",
      "url": "https://github.com/MyCryptoHQ/MyCrypto/releases"
    }
  ],
  "installinfo": [
    {
      "version": "Not Installed",
      "size": "Not Installed",
      "tag": "Not Installed",
      "status": "Not Installed"
    }
  ]
}
